sqlalchemy_mptt/__init__.py
sqlalchemy_mptt/events.py
sqlalchemy_mptt/mixins.py
oy_libs_sqlalchemy_mptt-0.2.4.dist-info/LICENSE.txt
oy_libs_sqlalchemy_mptt-0.2.4.dist-info/METADATA
oy_libs_sqlalchemy_mptt-0.2.4.dist-info/WHEEL
oy_libs_sqlalchemy_mptt-0.2.4.dist-info/top_level.txt
oy_libs_sqlalchemy_mptt-0.2.4.dist-info/RECORD
