Metadata-Version: 2.1
Name: oy-libs-sqlalchemy-mptt
Version: 0.2.4
Summary: SQLAlchemy MPTT mixins (Nested Sets)
Home-page: http://github.com/mush42/sqlalchemy_mptt/
Author: Svintsov Dmitry
Author-email: sacrud@uralbash.ru
License: MIT
Platform: UNKNOWN
Classifier: Development Status :: 5 - Production/Stable
Classifier: Environment :: Console
Classifier: Environment :: Web Environment
Classifier: Intended Audience :: Developers
Classifier: Natural Language :: English
Classifier: Operating System :: OS Independent
Classifier: Programming Language :: Python
Classifier: Programming Language :: Python :: 2.6
Classifier: Programming Language :: Python :: 2.7
Classifier: Programming Language :: Python :: 3
Classifier: Programming Language :: Python :: 3.4
Classifier: Programming Language :: Python :: 3.5
Classifier: Programming Language :: Python :: 3.6
Classifier: Framework :: Pyramid
Classifier: Framework :: Flask
Classifier: Topic :: Internet
Classifier: Topic :: Database
Classifier: License :: OSI Approved :: MIT License
Requires-Dist: SQLAlchemy (>=1.0.0)
